{
  "mrbeas": {
    "UCX6OQ3DkcsbYNE6H8uQQuVA": {
      "title": "MrBeast",
      "url": "https://www.youtube.com/channel/UCX6OQ3DkcsbYNE6H8uQQuVA"
    },
    "UCIPPMRA040LQr5QPyJEbmXA": {
      "title": "MrBeast Gaming",
      "url": "https://www.youtube.com/channel/UCIPPMRA040LQr5QPyJEbmXA"
    },
    "UCDifkiOICEJ-hiVAvCQlpNA": {
      "title": "MrBeast हिन्दी",
      "url": "https://www.youtube.com/channel/UCDifkiOICEJ-hiVAvCQlpNA"
    },
    "UC4-79UOlP48-QNGgCko5p2g": {
      "title": "MrBeast 2",
      "url": "https://www.youtube.com/channel/UC4-79UOlP48-QNGgCko5p2g"
    },
    "UCggERuskO1F6XKwor-Pvkww": {
      "title": "MrBeast Brasil",
      "url": "https://www.youtube.com/channel/UCggERuskO1F6XKwor-Pvkww"
    },
    "UCluBATXIP9doWvougjUVUGQ": {
      "title": "MrBeast На Русском",
      "url": "https://www.youtube.com/channel/UCluBATXIP9doWvougjUVUGQ"
    }
  },
  "mrbeast": {
    "UCX6OQ3DkcsbYNE6H8uQQuVA": {
      "title": "MrBeast",
      "url": "https://www.youtube.com/channel/UCX6OQ3DkcsbYNE6H8uQQuVA"
    },
    "UCIPPMRA040LQr5QPyJEbmXA": {
      "title": "MrBeast Gaming",
      "url": "https://www.youtube.com/channel/UCIPPMRA040LQr5QPyJEbmXA"
    },
    "UCDifkiOICEJ-hiVAvCQlpNA": {
      "title": "MrBeast हिन्दी",
      "url": "https://www.youtube.com/channel/UCDifkiOICEJ-hiVAvCQlpNA"
    },
    "UC4-79UOlP48-QNGgCko5p2g": {
      "title": "MrBeast 2",
      "url": "https://www.youtube.com/channel/UC4-79UOlP48-QNGgCko5p2g"
    },
    "UCggERuskO1F6XKwor-Pvkww": {
      "title": "MrBeast Brasil",
      "url": "https://www.youtube.com/channel/UCggERuskO1F6XKwor-Pvkww"
    },
    "UCluBATXIP9doWvougjUVUGQ": {
      "title": "MrBeast На Русском",
      "url": "https://www.youtube.com/channel/UCluBATXIP9doWvougjUVUGQ"
    }
  },
  "mrbea": {
    "UCX6OQ3DkcsbYNE6H8uQQuVA": {
      "title": "MrBeast",
      "url": "https://www.youtube.com/channel/UCX6OQ3DkcsbYNE6H8uQQuVA"
    },
    "UCzoFjzSkbrDD1GHsz2YNLig": {
      "title": "Mr Bean World",
      "url": "https://www.youtube.com/channel/UCzoFjzSkbrDD1GHsz2YNLig"
    },
    "UCkAGrHCLFmlK3H2kd6isipg": {
      "title": "Mr Bean",
      "url": "https://www.youtube.com/channel/UCkAGrHCLFmlK3H2kd6isipg"
    },
    "UCa8h6pyPTYw1zg7SkmAfGXw": {
      "title": "Mr Bean Hindi",
      "url": "https://www.youtube.com/channel/UCa8h6pyPTYw1zg7SkmAfGXw"
    },
    "UCqrKrE7yoCj0qYbhq57e_xw": {
      "title": "MrBea",
      "url": "https://www.youtube.com/channel/UCqrKrE7yoCj0qYbhq57e_xw"
    },
    "UCTNGr-HQljWJuebHS7xbfWg": {
      "title": "Mrbea",
      "url": "https://www.youtube.com/channel/UCTNGr-HQljWJuebHS7xbfWg"
    }
  },
  "mrbe": {
    "UCX6OQ3DkcsbYNE6H8uQQuVA": {
      "title": "MrBeast",
      "url": "https://www.youtube.com/channel/UCX6OQ3DkcsbYNE6H8uQQuVA"
    },
    "UCs1K59Be9p_hqdeR_8lqY3g": {
      "title": "mrbe",
      "url": "https://www.youtube.com/channel/UCs1K59Be9p_hqdeR_8lqY3g"
    },
    "UCAiLfjNXkNv24uhpzUgPa6A": {
      "title": "Beast Philanthropy",
      "url": "https://www.youtube.com/channel/UCAiLfjNXkNv24uhpzUgPa6A"
    },
    "UCIDdE7gtKBIGqeHvLknTGnA": {
      "title": "MrBe",
      "url": "https://www.youtube.com/channel/UCIDdE7gtKBIGqeHvLknTGnA"
    },
    "UC2Y5Hk1coj2kTUpNEwIBQxw": {
      "title": "MrBe",
      "url": "https://www.youtube.com/channel/UC2Y5Hk1coj2kTUpNEwIBQxw"
    },
    "UCRSNXKQERva5gDKiTBABJMw": {
      "title": "mrbe",
      "url": "https://www.youtube.com/channel/UCRSNXKQERva5gDKiTBABJMw"
    }
  },
  "m": {
    "UCmbNDD-DifF92QNbKvlF_SA": {
      "title": "M Prashant",
      "url": "https://www.youtube.com/channel/UCmbNDD-DifF92QNbKvlF_SA"
    },
    "UCfGz9n-RwIq00s9vij_15wg": {
      "title": "Tarot With M Singh®",
      "url": "https://www.youtube.com/channel/UCfGz9n-RwIq00s9vij_15wg"
    },
    "UCiMb-r3zqoPPAv3Ai4sPOpQ": {
      "title": "M For Microbiology",
      "url": "https://www.youtube.com/channel/UCiMb-r3zqoPPAv3Ai4sPOpQ"
    },
    "UCT7IPt6DFlKfxyWJ4TYdYEQ": {
      "title": "The M",
      "url": "https://www.youtube.com/channel/UCT7IPt6DFlKfxyWJ4TYdYEQ"
    },
    "UCG2CL6EUjG8TVT1Tpl9nJdg": {
      "title": "Ms Rachel - Toddler Learning Videos",
      "url": "https://www.youtube.com/channel/UCG2CL6EUjG8TVT1Tpl9nJdg"
    },
    "UCBBQAN_obRu2kJg6ojZZxfw": {
      "title": "M craft",
      "url": "https://www.youtube.com/channel/UCBBQAN_obRu2kJg6ojZZxfw"
    }
  },
  "MrBe": {
    "UCX6OQ3DkcsbYNE6H8uQQuVA": {
      "title": "MrBeast",
      "url": "https://www.youtube.com/channel/UCX6OQ3DkcsbYNE6H8uQQuVA"
    },
    "UCAiLfjNXkNv24uhpzUgPa6A": {
      "title": "Beast Philanthropy",
      "url": "https://www.youtube.com/channel/UCAiLfjNXkNv24uhpzUgPa6A"
    },
    "UCs1K59Be9p_hqdeR_8lqY3g": {
      "title": "mrbe",
      "url": "https://www.youtube.com/channel/UCs1K59Be9p_hqdeR_8lqY3g"
    },
    "UC2Y5Hk1coj2kTUpNEwIBQxw": {
      "title": "MrBe",
      "url": "https://www.youtube.com/channel/UC2Y5Hk1coj2kTUpNEwIBQxw"
    },
    "UCRSNXKQERva5gDKiTBABJMw": {
      "title": "mrbe",
      "url": "https://www.youtube.com/channel/UCRSNXKQERva5gDKiTBABJMw"
    },
    "UCIDdE7gtKBIGqeHvLknTGnA": {
      "title": "MrBe",
      "url": "https://www.youtube.com/channel/UCIDdE7gtKBIGqeHvLknTGnA"
    }
  },
  "beast": {
    "UCX6OQ3DkcsbYNE6H8uQQuVA": {
      "title": "MrBeast",
      "url": "https://www.youtube.com/channel/UCX6OQ3DkcsbYNE6H8uQQuVA"
    },
    "UCPaEZzOqk5EvG_-RCXktPPA": {
      "title": "The Beast Generation",
      "url": "https://www.youtube.com/channel/UCPaEZzOqk5EvG_-RCXktPPA"
    },
    "UCNSdjX4ry9fICqeObdZPAZQ": {
      "title": "Flying Beast",
      "url": "https://www.youtube.com/channel/UCNSdjX4ry9fICqeObdZPAZQ"
    },
    "UCUaT_39o1x6qWjz7K2pWcgw": {
      "title": "Beast Reacts",
      "url": "https://www.youtube.com/channel/UCUaT_39o1x6qWjz7K2pWcgw"
    },
    "UCAiLfjNXkNv24uhpzUgPa6A": {
      "title": "Beast Philanthropy",
      "url": "https://www.youtube.com/channel/UCAiLfjNXkNv24uhpzUgPa6A"
    },
    "UCKomAg8jFmqVoiNhVYjwZSw": {
      "title": "Beast",
      "url": "https://www.youtube.com/channel/UCKomAg8jFmqVoiNhVYjwZSw"
    }
  },
  "mr": {
    "UCX6OQ3DkcsbYNE6H8uQQuVA": {
      "title": "MrBeast",
      "url": "https://www.youtube.com/channel/UCX6OQ3DkcsbYNE6H8uQQuVA"
    },
    "UCEjA5F8lg5ntTbS7WDeRDFA": {
      "title": "Mr.Heang Update",
      "url": "https://www.youtube.com/channel/UCEjA5F8lg5ntTbS7WDeRDFA"
    },
    "UCNKPAIbE1uap5Imyk9jQUQQ": {
      "title": "Mr Hindi Explainer",
      "url": "https://www.youtube.com/channel/UCNKPAIbE1uap5Imyk9jQUQQ"
    },
    "UCynLtJ9E2c34bui4ON0ovGw": {
      "title": "Mr Tumble and Friends",
      "url": "https://www.youtube.com/channel/UCynLtJ9E2c34bui4ON0ovGw"
    },
    "UC3XVA_Ii4aEvGQTzs3nIcSg": {
      "title": "Mr. Chottu",
      "url": "https://www.youtube.com/channel/UC3XVA_Ii4aEvGQTzs3nIcSg"
    },
    "UCHB01PwfQR4fPRJXemc__Hg": {
      "title": "Mr & Mrs Dhesi USA ਢੇਸੀ",
      "url": "https://www.youtube.com/channel/UCHB01PwfQR4fPRJXemc__Hg"
    }
  }
}